{
  "admin_accounts_empty_browse": "Aucun compte dans cet onglet. Utilisez la recherche par e-mail ou UID.",
  "admin_accounts_empty_search": "Essayez l'e-mail, l'UID ou le nom affiché",
  "admin_accounts_empty_title": "Aucun compte trouvé",
  "admin_accounts_load_error_title": "Impossible de charger les comptes",
  "admin_accounts_retry": "Réessayer",
  "admin_accounts_subtitle": "Utilisateurs, établissements et équipe interne — tous issus de users/{uid} dans Firestore.",
  "admin_accounts_tab_affiliates": "Affiliés",
  "admin_accounts_tab_business": "Établissements",
  "admin_accounts_tab_consumers": "Utilisateurs",
  "admin_accounts_tab_team": "Équipe",
  "admin_accounts_title": "Comptes",
  "admin_active": "Actif",
  "admin_add_bilingual_feature": "Ajouter une fonctionnalité bilingue",
  "admin_add_feature": "Ajouter une fonctionnalité",
  "admin_add_feature_error": "Veuillez ajouter au moins une fonctionnalité",
  "admin_badge_text": "Texte du badge",
  "admin_basic_info": "Informations de base",
  "admin_business_field_subscription": "Données Stripe / abonnement (JSON)",
  "admin_business_field_tier": "Niveau d'abonnement",
  "admin_business_limits_button": "Limites établissement",
  "admin_business_mgmt_sub_embedded": "Limites et niveaux accessibles depuis chaque ligne. Utilisateurs :",
  "admin_business_mgmt_sub_full": "Profils établissements paginés. Utilisateurs :",
  "admin_business_mgmt_title": "Gestion des établissements",
  "admin_business_mgmt_title_embedded": "Comptes établissement",
  "admin_clear_reset_all": "Effacer et tout réinitialiser",
  "admin_create_new_plan": "Créer un nouveau plan",
  "admin_create_plan_desc": "Concevoir un nouveau plan d'abonnement",
  "admin_credit_packs": "Packs de crédits",
  "admin_credits": "Crédits",
  "admin_day": "Jour",
  "admin_delete_pack_confirm": "Supprimer ce pack de crédits ?",
  "admin_delete_plan_confirm": "Voulez-vous vraiment supprimer ce plan ? Cette action est irréversible !",
  "admin_delete_plan_error": "Échec de la suppression du plan",
  "admin_delete_plan_success": "Plan supprimé avec succès !",
  "admin_delete_user_confirm": "Supprimer définitivement ce compte ? L'utilisateur sera retiré de l'authentification, Firestore, du contenu associé et des préfixes Storage connus. Cette action est irréversible.",
  "admin_delete_user_done": "Utilisateur et {{count}} enregistrements Firestore associés supprimés.{{storage}}",
  "admin_delete_user_storage": " Nettoyage Storage effectué pour {{count}} préfixe(s) de chemin.",
  "admin_description": "Description",
  "admin_description_ar": "Description (arabe)",
  "admin_description_en": "Description (anglais)",
  "admin_design": "Design",
  "admin_discount": "Remise",
  "admin_duration_type": "Type de durée",
  "admin_duration_value": "Valeur de durée",
  "admin_edit_plan": "Modifier le plan",
  "admin_edit_plan_desc": "Mettre à jour les détails du plan d'abonnement",
  "admin_enter_plan_name": "Veuillez saisir un nom de plan",
  "admin_feature": "Fonctionnalité",
  "admin_feature_ar": "Fonctionnalité (arabe)…",
  "admin_feature_en": "Fonctionnalité (anglais)…",
  "admin_features": "Fonctionnalités",
  "admin_fetch_plan_error": "Échec du chargement du plan",
  "admin_for_partners": "Pour les partenaires",
  "admin_for_users": "Pour les utilisateurs",
  "admin_geo_city_label": "{{step}} — Ville",
  "admin_geo_city_placeholder": "Rechercher une ville…",
  "admin_geo_city_resolved": "Ville sélectionnée : <strong>{{city}}</strong>{{region}}{{country}}",
  "admin_geo_city_search_disabled": "Terminez les étapes précédentes pour activer la recherche de ville.",
  "admin_geo_city_select_country": "Sélectionnez d'abord le pays",
  "admin_geo_city_select_state": "Sélectionnez d'abord la région/province",
  "admin_geo_city_selected": "Ville sélectionnée : {{city}}{{region}}{{country}}",
  "admin_geo_country_label": "1 — Pays",
  "admin_geo_country_placeholder": "Sélectionner un pays…",
  "admin_geo_country_search": "Rechercher un pays par les premières lettres…",
  "admin_geo_no_countries": "Aucun pays correspondant",
  "admin_geo_no_results": "Aucun résultat.",
  "admin_geo_no_results_query": "Aucun résultat pour « {{query}} »",
  "admin_geo_no_states": "Aucune région/province correspondante",
  "admin_geo_state_label": "2 — Région / province",
  "admin_geo_state_placeholder": "Sélectionner une région/province…",
  "admin_geo_state_search": "Rechercher une région par les premières lettres…",
  "admin_hide_preview": "Masquer l'aperçu",
  "admin_home_accounts_cta": "Ouvrir le gestionnaire de comptes",
  "admin_home_ai_cover_cost": "Couverture d'invitation IA (variable Functions INVITATION_AI_IMAGE_CREDIT_COST) : {{cost}} crédits par génération — alignez cette valeur sur Vercel pour /api/generate-image.",
  "admin_home_all_invitations": "Toutes les invitations chargées",
  "admin_home_btn_profile": "Profil",
  "admin_home_btn_view": "Voir",
  "admin_home_business_preview": "Établissements (échantillon)",
  "admin_home_col_business": "Établissement",
  "admin_home_col_created": "Créé",
  "admin_home_col_credits": "Crédits",
  "admin_home_col_display_name": "Nom affiché",
  "admin_home_col_email": "E-mail",
  "admin_home_col_plan": "Plan",
  "admin_home_col_title": "Titre",
  "admin_home_col_type": "Type",
  "admin_home_consumers_preview": "Utilisateurs (échantillon)",
  "admin_home_credits_line": "payés {{paid}} · gratuits {{free}}",
  "admin_home_inv_private": "Privée",
  "admin_home_inv_public": "Publique",
  "admin_home_invitations_manage": "Pour la modération et les actions groupées, utilisez Gestion des invitations dans la barre latérale.",
  "admin_home_latest_invitations": "Dernières invitations",
  "admin_home_latest_invitations_hint": "Publiques et privées — les plus récentes en premier.",
  "admin_home_loading": "Chargement…",
  "admin_home_no_businesses": "Aucun établissement dans cet échantillon.",
  "admin_home_no_consumers": "Aucun utilisateur dans cet échantillon.",
  "admin_home_no_invitations": "Aucune invitation pour l'instant.",
  "admin_home_preview_hint": "Affichage d'un petit échantillon. Listes complètes, bannissements et rôles :",
  "admin_home_reports_pending": "Signalements en attente : {{count}}",
  "admin_home_stat_businesses": "Établissements",
  "admin_home_stat_consumers": "Utilisateurs",
  "admin_home_stat_invitations": "Invitations (publiques + privées)",
  "admin_home_stat_team": "Équipe (admin / staff / support)",
  "admin_home_subtitle": "Métriques agrégées et aperçus rapides. La gestion détaillée se trouve sous Comptes.",
  "admin_home_tab_businesses": "Établissements",
  "admin_home_tab_invitations": "Invitations",
  "admin_home_tab_overview": "Vue d'ensemble",
  "admin_home_tab_users": "Utilisateurs",
  "admin_home_title": "Tableau de bord admin",
  "admin_icon": "Icône",
  "admin_invitations_block": "Bloquer",
  "admin_invitations_confirm_action": "Confirmer : {{action}} ?",
  "admin_invitations_date": "Date",
  "admin_invitations_delete": "Supprimer",
  "admin_invitations_host": "Hôte",
  "admin_invitations_lead": "Filtrer par type (publique / privée / rencontre) — supprimer, bloquer ou republier.",
  "admin_invitations_republish": "Republier",
  "admin_invitations_status": "Statut",
  "admin_invitations_title": "Invitations",
  "admin_invitations_title_col": "Titre",
  "admin_invitations_type": "Type",
  "admin_invitations_type_all": "Toutes",
  "admin_invitations_type_dating": "Rencontre",
  "admin_invitations_type_private": "Privée",
  "admin_invitations_type_public": "Publique",
  "admin_link_accounts_business": "Comptes → Établissements",
  "admin_link_accounts_consumers": "Comptes → Utilisateurs",
  "admin_link_grant_credits": "Accorder des crédits",
  "admin_link_system_tools": "Outils système",
  "admin_live_preview": "Aperçu en direct",
  "admin_loading_plan": "Chargement du plan…",
  "admin_mark_as_recommended": "Marquer comme recommandé",
  "admin_month": "Mois",
  "admin_nav_audit": "Journal d'audit",
  "admin_nav_backups": "Instantanés de code",
  "admin_nav_billing": "Facturation",
  "admin_nav_chat": "Chat et communauté",
  "admin_nav_content": "Contenu",
  "admin_nav_dashboard": "Tableau de bord",
  "admin_nav_grant_credits": "Accorder des crédits",
  "admin_nav_group_accounts": "Comptes",
  "admin_nav_item_accounts": "Tous les comptes",
  "admin_nav_migration": "Migration",
  "admin_nav_notifications": "Notifications",
  "admin_nav_ops": "Opérations",
  "admin_nav_overview": "Vue d'ensemble",
  "admin_nav_plans": "Plans et packs",
  "admin_nav_safety": "Sécurité",
  "admin_nav_settings": "Paramètres",
  "admin_nav_subscriptions": "Abonnements et crédits",
  "admin_nav_system_tools": "Outils système",
  "admin_negative_price": "Le prix ne peut pas être négatif",
  "admin_no_features_added": "Aucune fonctionnalité ajoutée",
  "admin_no_packs_found": "Aucun pack de crédits trouvé",
  "admin_no_plans_found": "Aucun plan trouvé",
  "admin_off": "DÉSACTIVÉ",
  "admin_original_price": "Prix d'origine",
  "admin_panel": "Panneau d'administration",
  "admin_partner": "Partenaire",
  "admin_partner_plan": "Plan Établissement",
  "admin_places_already_imported": "Cet établissement a déjà été importé — la publication mettra à jour l'enregistrement <code>restaurants/{{docId}}</code>.",
  "admin_places_already_imported_plain": "Cet établissement a déjà été importé — la publication mettra à jour l'enregistrement",
  "admin_places_aria_search": "Recherche Google Places",
  "admin_places_business_list_link": "Annuaire des établissements (/restaurants)",
  "admin_places_business_profile_link": "Page de profil (/business/{{id}})",
  "admin_places_business_search_label": "{{step}} — Rechercher un établissement",
  "admin_places_business_search_placeholder": "Rechercher un restaurant ou un café à {{city}}…",
  "admin_places_complete_geo_first": "Terminez d'abord la sélection du pays et de la ville",
  "admin_places_connection_failed": "Échec de la connexion",
  "admin_places_cover_alt": "Image de l'établissement",
  "admin_places_cover_alt_preview": "Aperçu de la couverture",
  "admin_places_cover_saved": "Image de couverture enregistrée dans Firebase Storage.",
  "admin_places_fetch_preview": "Récupérer l'aperçu",
  "admin_places_fetching": "Récupération des données Google et de l'image d'aperçu…",
  "admin_places_google_fetch_failed": "Échec de la récupération des données Google : {{message}}",
  "admin_places_google_photo_failed": "Impossible de charger la photo Google : {{message}}",
  "admin_places_lead": "Sélectionnez la région, recherchez l'établissement, puis récupérez l'aperçu pour charger les données et l'image en mémoire. Quand tout est prêt, cliquez sur Publier vers Firestore — l'image est envoyée vers Storage, puis le document est enregistré.",
  "admin_places_location_filter": "Filtre de localisation",
  "admin_places_login_required": "Connexion administrateur requise",
  "admin_places_new_preview": "Nouvel aperçu",
  "admin_places_no_google_image": "Aucune image Google — la couverture par défaut sera utilisée lors de la publication.",
  "admin_places_place_resolve_failed": "Impossible de résoudre l'établissement depuis Google. Essayez un autre résultat.",
  "admin_places_preview_failed": "Échec de la récupération de l'aperçu",
  "admin_places_preview_in_memory": "Aperçu en mémoire — pas encore envoyé vers Firebase Storage.",
  "admin_places_publish": "Publier vers Firestore",
  "admin_places_publish_failed": "Échec de la publication vers Firestore",
  "admin_places_publish_storage_failed": "Échec de l'envoi de l'image de couverture vers Firebase Storage. Vérifiez FIREBASE_SERVICE_ACCOUNT_JSON et FIREBASE_STORAGE_BUCKET.",
  "admin_places_publishing": "Publication…",
  "admin_places_rate_limited": "Limite de débit dépassée — patientez un instant et réessayez",
  "admin_places_refetch_preview": "Actualiser l'aperçu",
  "admin_places_sign_in_admin": "Se connecter en tant qu'administrateur",
  "admin_places_title": "Importer un établissement depuis Google Places",
  "admin_places_visible_in": "Visible dans",
  "admin_plan_create_success": "Plan créé avec succès !",
  "admin_plan_management": "Gestion des plans",
  "admin_plan_mgmt_desc": "Créer et gérer les plans d'abonnement",
  "admin_plan_name": "Nom du plan",
  "admin_plan_name_ar": "Nom du plan (arabe)",
  "admin_plan_name_en": "Nom du plan (anglais)",
  "admin_plan_not_found": "Plan introuvable !",
  "admin_plan_save_error": "Échec de l'enregistrement du plan : {{error}}",
  "admin_plan_type": "Type de plan",
  "admin_plan_update_success": "Plan mis à jour avec succès !",
  "admin_plans_cancel": "Annuler",
  "admin_plans_credit_packs": "Packs de crédits ({{count}})",
  "admin_plans_credits_amount": "Crédits",
  "admin_plans_delete": "Supprimer",
  "admin_plans_edit": "Modifier",
  "admin_plans_env_banner_production": "Environnement Production — actif",
  "admin_plans_env_banner_sandbox": "Environnement Sandbox — isolé",
  "admin_plans_env_confirm": "Définir planEnvironment=\"{{env}}\" sur ce document ?",
  "admin_plans_env_environment": "Environnement",
  "admin_plans_env_legacy_count": "{{count}} document(s) sans planEnvironment — traités comme production dans l'application. Utilisez → Sandbox pour isoler.",
  "admin_plans_env_load_failed": "Impossible de charger les plans depuis Firestore",
  "admin_plans_env_name": "Nom",
  "admin_plans_env_price": "Prix",
  "admin_plans_env_stripe": "Stripe",
  "admin_plans_env_title_production": "Plans Production",
  "admin_plans_env_title_sandbox": "Plans Sandbox",
  "admin_plans_lead_production": "Inclut les plans production et hérités sans planEnvironment (affichés dans l'application).",
  "admin_plans_lead_sandbox": "Uniquement les documents avec planEnvironment = sandbox. Créez un nouveau plan ou déplacez des plans depuis Production.",
  "admin_plans_legacy_badge": "Hérité",
  "admin_plans_name_placeholder": "Nom du plan",
  "admin_plans_new_plan": "Nouveau plan",
  "admin_plans_no_packs": "Aucun pack — ajoutez manuellement dans Firestore avec planEnvironment=\"{{env}}\"",
  "admin_plans_no_sandbox_docs": "Aucun document avec planEnvironment=sandbox. Les plans hérités sans ce champ n'apparaissent que sous Plans Production.",
  "admin_plans_pack_col": "Pack",
  "admin_plans_plans_tab": "Plans ({{count}})",
  "admin_plans_price_placeholder": "Prix USD",
  "admin_plans_save": "Enregistrer",
  "admin_plans_to_production": "→ Production",
  "admin_plans_to_sandbox": "→ Sandbox",
  "admin_price": "Prix",
  "admin_price_id": "ID de prix",
  "admin_pricing": "Tarification",
  "admin_published": "Publié",
  "admin_recommended": "Recommandé",
  "admin_save_plan": "Enregistrer le plan",
  "admin_saving": "Enregistrement…",
  "admin_show_badge": "Afficher le badge",
  "admin_show_preview": "Afficher l'aperçu",
  "admin_status": "Statut",
  "admin_stripe_hint": "Récupérez cette valeur depuis votre tableau de bord Stripe",
  "admin_stripe_integration": "Intégration Stripe",
  "admin_subscription_plans": "Plans d'abonnement",
  "admin_sync_all_confirm": "Synchroniser les plans et packs de crédits depuis le code ? La correspondance se fera par ID/Niveau/PriceID et les enregistrements existants seront mis à jour.",
  "admin_sync_error": "Échec de la synchronisation : {{error}}",
  "admin_sync_from_code": "Synchroniser tout depuis le code",
  "admin_sync_success": "Synchronisation terminée !\nPlans : {{planImported}} nouveaux, {{planUpdated}} mis à jour\nPacks de crédits : {{packImported}} nouveaux, {{packUpdated}} mis à jour",
  "admin_user": "Utilisateur",
  "admin_user_mgmt_sub_affiliates": "Partenaires qui partagent des liens de parrainage. Ils se connectent sur /affiliate (mobile ou bureau).",
  "admin_user_mgmt_sub_consumers": "Comptes utilisateurs paginés (rôle : user). Les crédits sont gérés dans",
  "admin_user_mgmt_sub_credits": "Crédits utilisateurs :",
  "admin_user_mgmt_sub_full": "Navigation paginée. Les comptes établissement se trouvent sous",
  "admin_user_mgmt_sub_team": "Comptes admin, staff et support. Les changements de rôle passent par des Cloud Functions sécurisées.",
  "admin_user_mgmt_sub_tools": "Maintenance :",
  "admin_user_mgmt_title": "Gestion des utilisateurs",
  "admin_user_mgmt_title_affiliates": "Partenaires affiliés",
  "admin_user_mgmt_title_consumers": "Utilisateurs",
  "admin_user_mgmt_title_team": "Équipe et rôles",
  "admin_user_plan": "Plan utilisateur",
  "admin_year": "Année"
}
